[{"id":"32754","patientinfo":"{\n  \"resourceType\": \"Patient\",\n  \"id\": \"32754\",\n  \"meta\": {\n    \"versionId\": \"40\",\n    \"lastUpdated\": \"2017-11-07T22:25:19.827-05:00\"\n  },\n  \"text\": {\n    \"status\": \"generated\",\n    \"div\": \"\u003cdiv xmlns=\\\"http://www.w3.org/1999/xhtml\\\"\u003e\u003cdiv class=\\\"hapiHeaderText\\\"\u003eTestPatch1 \u003cb\u003eCHARLTON \u003c/b\u003e\u003c/div\u003e\u003ctable class=\\\"hapiPropertyTable\\\"\u003e\u003ctbody\u003e\u003ctr\u003e\u003ctd\u003eAddress\u003c/td\u003e\u003ctd\u003e\u003cspan\u003e1234 tttttesting \u003c/span\u003e\u003cbr/\u003e\u003cspan\u003efairfax \u003c/span\u003e\u003cspan\u003eva \u003c/span\u003e\u003c/td\u003e\u003c/tr\u003e\u003ctr\u003e\u003ctd\u003eDate of birth\u003c/td\u003e\u003ctd\u003e\u003cspan\u003e07 October 2017\u003c/span\u003e\u003c/td\u003e\u003c/tr\u003e\u003c/tbody\u003e\u003c/table\u003e\u003c/div\u003e\"\n  },\n  \"name\": [\n    {\n      \"family\": \"Charlton\",\n      \"given\": [\n        \"TestPatch1\"\n      ]\n    }\n  ],\n  \"telecom\": [\n    {\n      \"value\": \"4567891234\"\n    }\n  ],\n  \"birthDate\": \"2017-10-07\",\n  \"address\": [\n    {\n      \"line\": [\n        \"1234 tttttesting\"\n      ],\n      \"city\": \"fairfax\",\n      \"state\": \"va\",\n      \"postalCode\": \"22030\"\n    }\n  ]\n}"}]